<?xml version="1.0" encoding="UTF-8"?>
<ColWidth xmlns:xsi="http://www.w3.org/2001/XMLSchema-instance"><Col Name="POINT:name" Width="136"/><Col Name="关联模板" Width="58"/><Col Name="类描述" Width="113"/><Col Name="所属类" Width="46"/><Col Name="同步源" Width="46"/><Col Name="DI:E0" Width="53"/><Col Name="DI:E1" Width="53"/><Col Name="DI:cosAlarm" Width="63"/><Col Name="DI:cosLog" Width="106"/><Col Name="POINT:label" Width="115"/><Col Name="POINT:pid" Width="0"/><Col Name="Variable:externTag" Width="178"/></ColWidth>
