<?xml version="1.0" encoding="UTF-8"?>
<NodesIndex xmlns:xsi="http://www.w3.org/2001/XMLSchema-instance"><DLFileHeader><LastUpdate>2014-09-10T17:04:52</LastUpdate><FileVersion>1410339892</FileVersion><Creator>CZMK_ENG</Creator></DLFileHeader><NodeInfo xmlns:xsi="http://www.w3.org/2001/XMLSchema-instance"><IDGroup><ID>1110</ID><TagName>YSC_YSX</TagName><Description></Description><Version>0</Version><Name>YSC_YSX</Name></IDGroup><Computer><ComputerName>CZMK_YSX1</ComputerName><IP_A>168.168.161.25</IP_A><IP_B></IP_B></Computer><Computer><ComputerName>CZMK_YSX2</ComputerName><IP_A>168.168.161.26</IP_A><IP_B></IP_B></Computer><SoftwareCfg><HMI>true</HMI><RTDB>true</RTDB><CACL>true</CACL><HDB>true</HDB><EVENT>true</EVENT><FEP>true</FEP></SoftwareCfg></NodeInfo></NodesIndex>
